cps_wb/__init__.py
cps_wb/_version.py
cps_wb/wikibase.py
cps_wb/wikilabel.py
cps_wb-1.0.0.dist-info/entry_points.txt
cps_wb-1.0.0.dist-info/licenses/LICENSE
cps_wb-1.0.0.dist-info/WHEEL
cps_wb-1.0.0.dist-info/METADATA
cps_wb-1.0.0.dist-info/RECORD
