Metadata-Version: 2.4
Name: cps_wb
Version: 1.0.0
Summary: CPS Wikibase
Author: Darron Broad
Requires-Python: >=3.9
Classifier: Programming Language :: Python :: 3
Classifier: Operating System :: OS Independent
License-File: LICENSE
Requires-Dist: WikibaseIntegrator>=0.12
Project-URL: Documentation, https://wiki.kewl.org/projects:wikibase
